CHANGELOG.rst
MANIFEST.in
README.rst
setup.py
docs/HISTORY.txt
mk/__init__.py
mk.recipe.pip.egg-info/PKG-INFO
mk.recipe.pip.egg-info/SOURCES.txt
mk.recipe.pip.egg-info/dependency_links.txt
mk.recipe.pip.egg-info/entry_points.txt
mk.recipe.pip.egg-info/namespace_packages.txt
mk.recipe.pip.egg-info/requires.txt
mk.recipe.pip.egg-info/top_level.txt
mk.recipe.pip.egg-info/zip-safe
mk/recipe/__init__.py
mk/recipe/pip/__init__.py