Metadata-Version: 1.1
Name: mk.recipe.pip
Version: 0.3
Summary: Use pip from buildout
Home-page: https://github.com/k4ml/mk.recipe.pip
Author: Kamal Mustafa
Author-email: kamal.mustafa@gmail.com
License: ZPL
Download-URL: https://github.com/k4ml/mk.recipe.pip/archive/master.zip#egg=mk.recipe.pip
Keywords: wsgi buildout
Platform: UNKNOWN
Classifier: Development Status :: 3 - Alpha
Classifier: Framework :: Buildout :: Recipe
Classifier: Intended Audience :: Developers
Classifier: Intended Audience :: System Administrators
Classifier: License :: OSI Approved :: Zope Public License
Classifier: Programming Language :: Python :: 2
Classifier: Programming Language :: Python :: 2.4
Classifier: Programming Language :: Python :: 2.5
Classifier: Programming Language :: Python :: 2.6
Classifier: Programming Language :: Python :: 2.7
Classifier: Programming Language :: Python :: 3
